terminal_controller.py
terminal_controller-0.1.9.dist-info/METADATA
terminal_controller-0.1.9.dist-info/WHEEL
terminal_controller-0.1.9.dist-info/entry_points.txt
terminal_controller-0.1.9.dist-info/licenses/LICENSE
terminal_controller-0.1.9.dist-info/RECORD
