Metadata-Version: 2.4
Name: terminal-controller
Version: 0.1.9
Summary: A Model Context Protocol (MCP) server for secure terminal command execution and file system operations
Project-URL: Homepage, https://github.com/GongRzhe/terminal-controller-mcp
Project-URL: Bug Tracker, https://github.com/GongRzhe/terminal-controller-mcp/issues
Author-email: GongRzhe <gongrzhe@gmail.com>
License: MIT License
License-File: LICENSE
Keywords: claude,command-line,mcp,terminal
Classifier: Development Status :: 4 - Beta
Classifier: Environment :: Console
Classifier: Intended Audience :: Developers
Classifier: License :: OSI Approved :: MIT License
Classifier: Programming Language :: Python :: 3
Classifier: Programming Language :: Python :: 3.11
Classifier: Topic :: Software Development :: Libraries :: Python Modules
Classifier: Topic :: Utilities
Requires-Python: >=3.11
Requires-Dist: httpx>=0.25.0
Requires-Dist: mcp[cli]>=1.3.0
